SSRS/__init__.py
SSRS/schemas.py
samples/FindItem.py
samples/GetParameters.py
samples/ListDir.py
samples/ListMethods.py
samples/LoadReport.py
samples/__init__.py
samples/connection_data.py
samples/context.py
samples/test.py
pySSRS2-2.0.1.dist-info/LICENSE
pySSRS2-2.0.1.dist-info/METADATA
pySSRS2-2.0.1.dist-info/WHEEL
pySSRS2-2.0.1.dist-info/top_level.txt
pySSRS2-2.0.1.dist-info/RECORD
